pymerlin/__init__.py
pymerlin/clock.py
pymerlin/duration.py
pymerlin/model_actions.py
pymerlin/reactions.py
pymerlin/_internal/README.md
pymerlin/_internal/_cell_type.py
pymerlin/_internal/_condition.py
pymerlin/_internal/_context.py
pymerlin/_internal/_decorators.py
pymerlin/_internal/_directive_type.py
pymerlin/_internal/_effect_trait.py
pymerlin/_internal/_framework.py
pymerlin/_internal/_gateway.py
pymerlin/_internal/_globals.py
pymerlin/_internal/_input_type.py
pymerlin/_internal/_model_type.py
pymerlin/_internal/_output_type.py
pymerlin/_internal/_plot.py
pymerlin/_internal/_py4j_utilities.py
pymerlin/_internal/_querier_adapter.py
pymerlin/_internal/_registrar.py
pymerlin/_internal/_resource.py
pymerlin/_internal/_schedule.py
pymerlin/_internal/_serialized_value.py
pymerlin/_internal/_spawn_helpers.py
pymerlin/_internal/_task_factory.py
pymerlin/_internal/_task_specification.py
pymerlin/_internal/_task_status.py
pymerlin/_internal/_threaded_task.py
pymerlin/_internal/jars/pymerlin.jar
pymerlin-0.0.9.dist-info/METADATA
pymerlin-0.0.9.dist-info/WHEEL
pymerlin-0.0.9.dist-info/licenses/LICENSE
pymerlin-0.0.9.dist-info/RECORD
