Metadata-Version: 2.3
Name: pymerlin
Version: 0.0.9
Summary: Python mission modeling framework for Aerie
Project-URL: Homepage, https://mattdailis.github.io/pymerlin
Project-URL: Documentation, https://mattdailis.github.io/pymerlin
Project-URL: Repository, https://github.com/mattdailis/pymerlin
Project-URL: Bug Tracker, https://github.com/mattdailis/pymerlin/issues
Project-URL: Changelog, https://github.com/mattdailis/pymerlin/blob/main/CHANGELOG.md
Author-email: Matthew Dailis <matthew.l.dailis@jpl.nasa.gov>
License: MIT License
License-File: LICENSE
Keywords: aerie,discrete event,merlin,simulation
Classifier: Development Status :: 2 - Pre-Alpha
Classifier: Programming Language :: Python
Requires-Python: >=3.11
Requires-Dist: py4j>=0.10.9.7
Provides-Extra: plotting
Requires-Dist: bokeh>=3.4.2; extra == 'plotting'
Requires-Dist: numpy>=2.0.0; extra == 'plotting'
